tests/test_autoregister.py
tests/base.py
tests/urls_root_with_prefix.py
tests/test_urlpatterns.py
tests/api_autoregister.py
tests/test_response.py
tests/test_apiroot.py
tests/__init__.py
tests/test_api.py
tests/urls_root_with_trailing_slash.py
tests/urls_root_without_prefix.py
tests/urls_autoregister.py
tests/test_resource.py
tests/test_context.py
tests/artest/models.py
tests/artest/__init__.py
tests/artest/restapi.py
restosaur/forms.py
restosaur/responses.py
restosaur/resource.py
restosaur/dispatch.py
restosaur/settings.py
restosaur/urltemplate.py
restosaur/__init__.py
restosaur/utils.py
restosaur/apps.py
restosaur/representations.py
restosaur/loading.py
restosaur/serializers.py
restosaur/decorators.py
restosaur/context.py
restosaur/exceptions.py
restosaur/filters.py
restosaur/contentnegotiation.py
restosaur/headers.py
restosaur/contrib/apiroot.py
restosaur/contrib/__init__.py
restosaur-0.6.8.dist-info/RECORD
restosaur-0.6.8.dist-info/zip-safe
restosaur-0.6.8.dist-info/WHEEL
restosaur-0.6.8.dist-info/METADATA
restosaur-0.6.8.dist-info/DESCRIPTION.rst
restosaur-0.6.8.dist-info/top_level.txt
restosaur-0.6.8.dist-info/metadata.json
